watcher_tempest_plugin/__init__.py
watcher_tempest_plugin/config.py
watcher_tempest_plugin/infra_optim_clients.py
watcher_tempest_plugin/plugin.py
watcher_tempest_plugin/utils.py
watcher_tempest_plugin/services/__init__.py
watcher_tempest_plugin/services/base.py
watcher_tempest_plugin/services/infra_optim/__init__.py
watcher_tempest_plugin/services/infra_optim/v1/__init__.py
watcher_tempest_plugin/services/infra_optim/v1/json/__init__.py
watcher_tempest_plugin/services/infra_optim/v1/json/api_microversion_fixture.py
watcher_tempest_plugin/services/infra_optim/v1/json/client.py
watcher_tempest_plugin/services/metric/__init__.py
watcher_tempest_plugin/services/metric/prometheus_client.py
watcher_tempest_plugin/services/metric/v1/__init__.py
watcher_tempest_plugin/services/metric/v1/json/__init__.py
watcher_tempest_plugin/services/metric/v1/json/client.py
watcher_tempest_plugin/tests/__init__.py
watcher_tempest_plugin/tests/api/__init__.py
watcher_tempest_plugin/tests/api/admin/__init__.py
watcher_tempest_plugin/tests/api/admin/base.py
watcher_tempest_plugin/tests/api/admin/test_action.py
watcher_tempest_plugin/tests/api/admin/test_action_plan.py
watcher_tempest_plugin/tests/api/admin/test_api_discovery.py
watcher_tempest_plugin/tests/api/admin/test_audit.py
watcher_tempest_plugin/tests/api/admin/test_audit_template.py
watcher_tempest_plugin/tests/api/admin/test_data_model.py
watcher_tempest_plugin/tests/api/admin/test_goal.py
watcher_tempest_plugin/tests/api/admin/test_scoring_engine.py
watcher_tempest_plugin/tests/api/admin/test_service.py
watcher_tempest_plugin/tests/api/admin/test_strategy.py
watcher_tempest_plugin/tests/client_functional/__init__.py
watcher_tempest_plugin/tests/client_functional/v1/__init__.py
watcher_tempest_plugin/tests/client_functional/v1/base.py
watcher_tempest_plugin/tests/client_functional/v1/test_action.py
watcher_tempest_plugin/tests/client_functional/v1/test_action_plan.py
watcher_tempest_plugin/tests/client_functional/v1/test_audit.py
watcher_tempest_plugin-3.6.0.dist-info/AUTHORS
watcher_tempest_plugin-3.6.0.dist-info/LICENSE
watcher_tempest_plugin-3.6.0.dist-info/METADATA
watcher_tempest_plugin-3.6.0.dist-info/WHEEL
watcher_tempest_plugin-3.6.0.dist-info/entry_points.txt
watcher_tempest_plugin-3.6.0.dist-info/pbr.json
watcher_tempest_plugin-3.6.0.dist-info/top_level.txt
watcher_tempest_plugin-3.6.0.dist-info/RECORD
